workflow/__init__.py
workflow/cli/__init__.py
workflow/cli/buckets.py
workflow/cli/configs.py
workflow/cli/main.py
workflow/cli/pipelines.py
workflow/cli/results.py
workflow/cli/run.py
workflow/cli/schedules.py
workflow/cli/workspace.py
workflow/daemons/__init__.py
workflow/daemons/audit.py
workflow/daemons/transfer.py
workflow/definitions/__init__.py
workflow/definitions/config.py
workflow/definitions/jsonschema.md
workflow/definitions/notify.py
workflow/definitions/work.py
workflow/definitions/workspace.py
workflow/examples/autocomplete.py
workflow/examples/function.py
workflow/examples/sample.svg
workflow/examples/sample.workflow.yml
workflow/exceptions.py
workflow/helpers/__init__.py
workflow/helpers/date.py
workflow/http/__init__.py
workflow/http/buckets.py
workflow/http/client.py
workflow/http/configs.py
workflow/http/context.py
workflow/http/pipelines.py
workflow/http/results.py
workflow/http/schedules.py
workflow/lifecycle/__init__.py
workflow/lifecycle/archive/__init__.py
workflow/lifecycle/archive/http.py
workflow/lifecycle/archive/posix.py
workflow/lifecycle/archive/s3.py
workflow/lifecycle/attempt.py
workflow/lifecycle/configure.py
workflow/lifecycle/execute.py
workflow/utils/__init__.py
workflow/utils/decorators.py
workflow/utils/format.py
workflow/utils/logger.py
workflow/utils/prompt.py
workflow/utils/read.py
workflow/utils/renderers.py
workflow/utils/tmate.sh
workflow/utils/validate.py
workflow/utils/variables.py
workflow/utils/write.py
workflow/workspaces/__init__.py
workflow/workspaces/chimefrb.yml
workflow/workspaces/development.yml
workflow/workspaces/site-dev.yml
workflow_core-1.11.6.dist-info/METADATA
workflow_core-1.11.6.dist-info/WHEEL
workflow_core-1.11.6.dist-info/entry_points.txt
workflow_core-1.11.6.dist-info/RECORD
