Metadata-Version: 2.3
Name: workflow.core
Version: 1.11.6
Summary: Workflow Core
License: MIT
Author: Shiny Brar
Author-email: charanjotbrar@gmail.com
Requires-Python: >=3.8.1,<4.0
Classifier: License :: OSI Approved :: MIT License
Classifier: Programming Language :: Python :: 3
Classifier: Programming Language :: Python :: 3.9
Classifier: Programming Language :: Python :: 3.10
Classifier: Programming Language :: Python :: 3.11
Classifier: Programming Language :: Python :: 3.12
Classifier: Programming Language :: Python :: 3.13
Requires-Dist: click (>=8.1,<9.0)
Requires-Dist: click-params (>=0.5,<0.6)
Requires-Dist: docker (>=6.1)
Requires-Dist: minio (>=7.2,<8.0)
Requires-Dist: pydantic (>=2.0,<3.0)
Requires-Dist: pydantic-settings (>=2.0,<3.0)
Requires-Dist: python-logging-loki (>=0.3,<0.4)
Requires-Dist: pyyaml (>=6.0,<7.0)
Requires-Dist: requests (>=2.31,<3.0)
Requires-Dist: rich (>=13.4,<14.0)
Requires-Dist: tenacity (>=8.2,<9.0)
Requires-Dist: toml (>=0.10,<0.11)
Project-URL: Documentation, https://chimefrb.github.io/workflow-docs/
Project-URL: Repository, https://github.com/chimefrb/workflow
